{
  "بنوك": {
    "net_flow_5d": -1986.76,
    "avg_change_5d": -1.73,
    "momentum_trend": "تباطؤ قوي",
    "leader": "1080",
    "leader_change": -0.05,
    "laggard": "1180",
    "laggard_change": -3.69,
    "stock_count": 10
  },
  "خدمات مالية": {
    "net_flow_5d": -131.44,
    "avg_change_5d": -2.98,
    "momentum_trend": "تباطؤ قوي",
    "leader": "4084",
    "leader_change": 0.84,
    "laggard": "1182",
    "laggard_change": -8.14,
    "stock_count": 12
  },
  "بتروكيماويات": {
    "net_flow_5d": 496.79,
    "avg_change_5d": -0.08,
    "momentum_trend": "تباطؤ قوي",
    "leader": "2380",
    "leader_change": 12.92,
    "laggard": "2040",
    "laggard_change": -6.54,
    "stock_count": 34
  },
  "فنادق": {
    "net_flow_5d": -41.89,
    "avg_change_5d": 2.09,
    "momentum_trend": "تباطؤ قوي",
    "leader": "1810",
    "leader_change": 3.31,
    "laggard": "1830",
    "laggard_change": -0.31,
    "stock_count": 3
  },
  "صناعية": {
    "net_flow_5d": 8.89,
    "avg_change_5d": -1.24,
    "momentum_trend": "تباطؤ قوي",
    "leader": "2120",
    "leader_change": 4.39,
    "laggard": "4145",
    "laggard_change": -10.25,
    "stock_count": 11
  },
  "طاقة": {
    "net_flow_5d": 1337.37,
    "avg_change_5d": 0.04,
    "momentum_trend": "تباطؤ",
    "leader": "2222",
    "leader_change": 1.02,
    "laggard": "2381",
    "laggard_change": -0.8,
    "stock_count": 4
  },
  "مرافق": {
    "net_flow_5d": 327.43,
    "avg_change_5d": -0.18,
    "momentum_trend": "تباطؤ قوي",
    "leader": "2083",
    "leader_change": 3.99,
    "laggard": "2082",
    "laggard_change": -4.27,
    "stock_count": 6
  },
  "زراعة وأغذية": {
    "net_flow_5d": 211.2,
    "avg_change_5d": -1.68,
    "momentum_trend": "تباطؤ قوي",
    "leader": "2280",
    "leader_change": 5.35,
    "laggard": "6012",
    "laggard_change": -13.66,
    "stock_count": 22
  },
  "نقل": {
    "net_flow_5d": -45.82,
    "avg_change_5d": -0.85,
    "momentum_trend": "تباطؤ قوي",
    "leader": "2190",
    "leader_change": 8.75,
    "laggard": "4260",
    "laggard_change": -6.84,
    "stock_count": 10
  },
  "أسمنت": {
    "net_flow_5d": -56.42,
    "avg_change_5d": -1.44,
    "momentum_trend": "تباطؤ قوي",
    "leader": "3060",
    "leader_change": 2.84,
    "laggard": "3050",
    "laggard_change": -5.16,
    "stock_count": 10
  },
  "رعاية صحية": {
    "net_flow_5d": -488.8,
    "avg_change_5d": -2.51,
    "momentum_trend": "تباطؤ قوي",
    "leader": "4007",
    "leader_change": 3.81,
    "laggard": "4018",
    "laggard_change": -6.18,
    "stock_count": 12
  },
  "تجزئة": {
    "net_flow_5d": 75.47,
    "avg_change_5d": -2.05,
    "momentum_trend": "تباطؤ",
    "leader": "4020",
    "leader_change": 11.8,
    "laggard": "4240",
    "laggard_change": -8.41,
    "stock_count": 17
  },
  "إعلام": {
    "net_flow_5d": -127.24,
    "avg_change_5d": -4.17,
    "momentum_trend": "تباطؤ قوي",
    "leader": "4070",
    "leader_change": -1.04,
    "laggard": "4071",
    "laggard_change": -9.36,
    "stock_count": 4
  },
  "عقار": {
    "net_flow_5d": -262.72,
    "avg_change_5d": -1.9,
    "momentum_trend": "تباطؤ قوي",
    "leader": "4327",
    "leader_change": 5.0,
    "laggard": "4220",
    "laggard_change": -8.89,
    "stock_count": 18
  },
  "اتصالات": {
    "net_flow_5d": 233.77,
    "avg_change_5d": -0.67,
    "momentum_trend": "تباطؤ قوي",
    "leader": "7010",
    "leader_change": 0.42,
    "laggard": "7020",
    "laggard_change": -1.84,
    "stock_count": 4
  },
  "تقنية": {
    "net_flow_5d": 261.6,
    "avg_change_5d": -1.21,
    "momentum_trend": "تسارع قوي",
    "leader": "7200",
    "leader_change": 2.56,
    "laggard": "7211",
    "laggard_change": -3.23,
    "stock_count": 4
  },
  "تأمين": {
    "net_flow_5d": -113.37,
    "avg_change_5d": -1.15,
    "momentum_trend": "تباطؤ قوي",
    "leader": "8313",
    "leader_change": 3.79,
    "laggard": "8010",
    "laggard_change": -4.34,
    "stock_count": 14
  }
}