{
  "بنوك": {
    "net_flow_5d": -543.22,
    "avg_change_5d": -1.71,
    "momentum_trend": "تباطؤ",
    "leader": "1120",
    "leader_change": -0.45,
    "laggard": "1080",
    "laggard_change": -3.29,
    "stock_count": 10
  },
  "خدمات مالية": {
    "net_flow_5d": -101.97,
    "avg_change_5d": 0.96,
    "momentum_trend": "تباطؤ قوي",
    "leader": "1213",
    "leader_change": 8.21,
    "laggard": "4083",
    "laggard_change": -3.59,
    "stock_count": 12
  },
  "بتروكيماويات": {
    "net_flow_5d": -180.24,
    "avg_change_5d": 0.0,
    "momentum_trend": "تباطؤ قوي",
    "leader": "2340",
    "leader_change": 14.66,
    "laggard": "2330",
    "laggard_change": -7.23,
    "stock_count": 34
  },
  "فنادق": {
    "net_flow_5d": 31.8,
    "avg_change_5d": 0.62,
    "momentum_trend": "تسارع قوي",
    "leader": "1833",
    "leader_change": 1.68,
    "laggard": "1830",
    "laggard_change": -0.32,
    "stock_count": 3
  },
  "صناعية": {
    "net_flow_5d": 225.09,
    "avg_change_5d": 4.24,
    "momentum_trend": "تسارع",
    "leader": "4144",
    "leader_change": 12.64,
    "laggard": "4142",
    "laggard_change": -3.77,
    "stock_count": 11
  },
  "طاقة": {
    "net_flow_5d": 563.77,
    "avg_change_5d": 5.1,
    "momentum_trend": "تسارع قوي",
    "leader": "2030",
    "leader_change": 17.51,
    "laggard": "2222",
    "laggard_change": -1.88,
    "stock_count": 3
  },
  "مرافق": {
    "net_flow_5d": -2.97,
    "avg_change_5d": 1.0,
    "momentum_trend": "مستقر",
    "leader": "2080",
    "leader_change": 1.91,
    "laggard": "5110",
    "laggard_change": 0.06,
    "stock_count": 5
  },
  "زراعة وأغذية": {
    "net_flow_5d": 205.26,
    "avg_change_5d": 3.47,
    "momentum_trend": "تباطؤ قوي",
    "leader": "6060",
    "leader_change": 19.16,
    "laggard": "2283",
    "laggard_change": -2.67,
    "stock_count": 21
  },
  "نقل": {
    "net_flow_5d": -230.48,
    "avg_change_5d": 0.18,
    "momentum_trend": "تباطؤ قوي",
    "leader": "4040",
    "leader_change": 2.69,
    "laggard": "4264",
    "laggard_change": -1.33,
    "stock_count": 10
  },
  "أسمنت": {
    "net_flow_5d": -65.91,
    "avg_change_5d": -1.27,
    "momentum_trend": "تباطؤ قوي",
    "leader": "3003",
    "leader_change": -0.27,
    "laggard": "3030",
    "laggard_change": -2.39,
    "stock_count": 10
  },
  "رعاية صحية": {
    "net_flow_5d": -109.24,
    "avg_change_5d": -0.14,
    "momentum_trend": "تباطؤ قوي",
    "leader": "4016",
    "leader_change": 4.0,
    "laggard": "4015",
    "laggard_change": -4.36,
    "stock_count": 12
  },
  "تجزئة": {
    "net_flow_5d": 240.37,
    "avg_change_5d": 1.62,
    "momentum_trend": "تسارع قوي",
    "leader": "4160",
    "leader_change": 15.92,
    "laggard": "4240",
    "laggard_change": -5.52,
    "stock_count": 16
  },
  "إعلام": {
    "net_flow_5d": -30.46,
    "avg_change_5d": 0.57,
    "momentum_trend": "تباطؤ قوي",
    "leader": "4070",
    "leader_change": 7.53,
    "laggard": "4072",
    "laggard_change": -3.84,
    "stock_count": 4
  },
  "عقار": {
    "net_flow_5d": 233.31,
    "avg_change_5d": 0.84,
    "momentum_trend": "تباطؤ",
    "leader": "4230",
    "leader_change": 7.16,
    "laggard": "4327",
    "laggard_change": -5.6,
    "stock_count": 18
  },
  "اتصالات": {
    "net_flow_5d": -65.23,
    "avg_change_5d": -0.67,
    "momentum_trend": "تباطؤ قوي",
    "leader": "7020",
    "leader_change": 3.75,
    "laggard": "7030",
    "laggard_change": -3.49,
    "stock_count": 4
  },
  "تقنية": {
    "net_flow_5d": -201.76,
    "avg_change_5d": -0.18,
    "momentum_trend": "تباطؤ قوي",
    "leader": "7200",
    "leader_change": 2.22,
    "laggard": "7202",
    "laggard_change": -1.6,
    "stock_count": 4
  },
  "تأمين": {
    "net_flow_5d": 66.13,
    "avg_change_5d": 2.68,
    "momentum_trend": "تباطؤ قوي",
    "leader": "8280",
    "leader_change": 12.22,
    "laggard": "8210",
    "laggard_change": -5.59,
    "stock_count": 13
  }
}