{
  "بنوك": {
    "net_flow_5d": -1315.11,
    "avg_change_5d": -1.75,
    "momentum_trend": "تباطؤ قوي",
    "leader": "1080",
    "leader_change": 0.0,
    "laggard": "1010",
    "laggard_change": -3.81,
    "stock_count": 10
  },
  "خدمات مالية": {
    "net_flow_5d": -380.37,
    "avg_change_5d": -0.53,
    "momentum_trend": "تباطؤ قوي",
    "leader": "1213",
    "leader_change": 18.58,
    "laggard": "1202",
    "laggard_change": -4.1,
    "stock_count": 12
  },
  "بتروكيماويات": {
    "net_flow_5d": -428.58,
    "avg_change_5d": -1.59,
    "momentum_trend": "تباطؤ قوي",
    "leader": "2310",
    "leader_change": 6.2,
    "laggard": "2320",
    "laggard_change": -7.66,
    "stock_count": 34
  },
  "فنادق": {
    "net_flow_5d": 19.72,
    "avg_change_5d": -1.59,
    "momentum_trend": "تباطؤ قوي",
    "leader": "1810",
    "leader_change": -0.48,
    "laggard": "1833",
    "laggard_change": -3.17,
    "stock_count": 3
  },
  "صناعية": {
    "net_flow_5d": -15.74,
    "avg_change_5d": -1.72,
    "momentum_trend": "تباطؤ",
    "leader": "4146",
    "leader_change": 7.26,
    "laggard": "2120",
    "laggard_change": -6.22,
    "stock_count": 11
  },
  "طاقة": {
    "net_flow_5d": -215.97,
    "avg_change_5d": -0.37,
    "momentum_trend": "تباطؤ قوي",
    "leader": "2030",
    "leader_change": 0.78,
    "laggard": "2381",
    "laggard_change": -2.5,
    "stock_count": 3
  },
  "مرافق": {
    "net_flow_5d": 159.09,
    "avg_change_5d": -3.32,
    "momentum_trend": "تباطؤ قوي",
    "leader": "2084",
    "leader_change": -2.17,
    "laggard": "2081",
    "laggard_change": -4.96,
    "stock_count": 5
  },
  "زراعة وأغذية": {
    "net_flow_5d": 235.42,
    "avg_change_5d": 1.99,
    "momentum_trend": "تسارع",
    "leader": "6050",
    "leader_change": 32.18,
    "laggard": "2281",
    "laggard_change": -4.25,
    "stock_count": 21
  },
  "نقل": {
    "net_flow_5d": -244.69,
    "avg_change_5d": -3.06,
    "momentum_trend": "تباطؤ قوي",
    "leader": "4264",
    "leader_change": -0.53,
    "laggard": "2190",
    "laggard_change": -5.85,
    "stock_count": 10
  },
  "أسمنت": {
    "net_flow_5d": 19.83,
    "avg_change_5d": 0.67,
    "momentum_trend": "تسارع",
    "leader": "3080",
    "leader_change": 3.92,
    "laggard": "3050",
    "laggard_change": -1.62,
    "stock_count": 10
  },
  "رعاية صحية": {
    "net_flow_5d": -285.31,
    "avg_change_5d": -2.02,
    "momentum_trend": "تباطؤ قوي",
    "leader": "4009",
    "leader_change": 0.5,
    "laggard": "4016",
    "laggard_change": -5.63,
    "stock_count": 12
  },
  "تجزئة": {
    "net_flow_5d": 62.74,
    "avg_change_5d": -0.72,
    "momentum_trend": "تسارع قوي",
    "leader": "4061",
    "leader_change": 5.74,
    "laggard": "4200",
    "laggard_change": -3.28,
    "stock_count": 16
  },
  "إعلام": {
    "net_flow_5d": -60.3,
    "avg_change_5d": -3.45,
    "momentum_trend": "تباطؤ قوي",
    "leader": "4070",
    "leader_change": -2.05,
    "laggard": "4210",
    "laggard_change": -6.82,
    "stock_count": 4
  },
  "عقار": {
    "net_flow_5d": -558.51,
    "avg_change_5d": -1.12,
    "momentum_trend": "تباطؤ قوي",
    "leader": "4325",
    "leader_change": 7.08,
    "laggard": "4280",
    "laggard_change": -6.63,
    "stock_count": 18
  },
  "اتصالات": {
    "net_flow_5d": -366.99,
    "avg_change_5d": -2.82,
    "momentum_trend": "تباطؤ قوي",
    "leader": "7010",
    "leader_change": -1.49,
    "laggard": "7040",
    "laggard_change": -3.69,
    "stock_count": 4
  },
  "تقنية": {
    "net_flow_5d": -272.16,
    "avg_change_5d": -0.76,
    "momentum_trend": "تباطؤ قوي",
    "leader": "7200",
    "leader_change": 5.31,
    "laggard": "7202",
    "laggard_change": -4.63,
    "stock_count": 4
  },
  "تأمين": {
    "net_flow_5d": -67.31,
    "avg_change_5d": -1.6,
    "momentum_trend": "تباطؤ قوي",
    "leader": "8250",
    "leader_change": 2.27,
    "laggard": "8230",
    "laggard_change": -7.92,
    "stock_count": 13
  }
}